jbang_jupyter_runner/__init__.py
jbang_jupyter_runner/labextension/package.json
jbang_jupyter_runner/labextension/static/565.11236c03868f7aa1e293.js
jbang_jupyter_runner/labextension/static/665.3e8b736f80ad6b311d7f.js
jbang_jupyter_runner/labextension/static/remoteEntry.727f42c4e2578cafd0f3.js
jbang_jupyter_runner/labextension/static/style.js
jbang_jupyter_runner/labextension/static/third-party-licenses.json
jbang_jupyter_runner-0.1.3.data/data/share/jupyter/labextensions/jbang-jupyter-runner/package.json
jbang_jupyter_runner-0.1.3.data/data/share/jupyter/labextensions/jbang-jupyter-runner/static/565.11236c03868f7aa1e293.js
jbang_jupyter_runner-0.1.3.data/data/share/jupyter/labextensions/jbang-jupyter-runner/static/665.3e8b736f80ad6b311d7f.js
jbang_jupyter_runner-0.1.3.data/data/share/jupyter/labextensions/jbang-jupyter-runner/static/remoteEntry.727f42c4e2578cafd0f3.js
jbang_jupyter_runner-0.1.3.data/data/share/jupyter/labextensions/jbang-jupyter-runner/static/style.js
jbang_jupyter_runner-0.1.3.data/data/share/jupyter/labextensions/jbang-jupyter-runner/static/third-party-licenses.json
jbang_jupyter_runner-0.1.3.data/data/share/jupyter/labextensions/jbang-jupyter-runner/install.json
jbang_jupyter_runner-0.1.3.dist-info/METADATA
jbang_jupyter_runner-0.1.3.dist-info/WHEEL
jbang_jupyter_runner-0.1.3.dist-info/licenses/LICENSE
jbang_jupyter_runner-0.1.3.dist-info/RECORD
